kwal_agents/__about__.py
kwal_agents/__init__.py
kwal_agents-0.0.1.dist-info/METADATA
kwal_agents-0.0.1.dist-info/WHEEL
kwal_agents-0.0.1.dist-info/licenses/LICENSE.txt
kwal_agents-0.0.1.dist-info/RECORD
