Metadata-Version: 2.3
Name: kwal-agents
Version: 0.0.1
Summary: WIP
Project-URL: Documentation, https://github.com/ZanSara/kwal-agents#readme
Project-URL: Issues, https://github.com/ZanSara/kwal-agents/issues
Project-URL: Source, https://github.com/ZanSara/kwal-agents
Author-email: ZanSara <sara@kwal.ai>
License-Expression: MIT
License-File: LICENSE.txt
Classifier: Development Status :: 4 - Beta
Classifier: Programming Language :: Python
Classifier: Programming Language :: Python :: 3.8
Classifier: Programming Language :: Python :: 3.9
Classifier: Programming Language :: Python :: 3.10
Classifier: Programming Language :: Python :: 3.11
Classifier: Programming Language :: Python :: 3.12
Classifier: Programming Language :: Python :: Implementation :: CPython
Classifier: Programming Language :: Python :: Implementation :: PyPy
Requires-Python: >=3.8
